Metadata-Version: 2.1
Name: odoo-addon-account_invoice_import_simple_pdf
Version: 18.0.1.1.0
Requires-Python: >=3.10
Requires-Dist: dateparser
Requires-Dist: odoo-addon-account_invoice_import==18.0.*
Requires-Dist: odoo==18.0.*
Requires-Dist: pymupdf
Requires-Dist: pypdf>=3.1.0
Requires-Dist: regex
Summary: Import simple PDF vendor bills
Home-page: https://github.com/OCA/edi
License: AGPL-3
Author: Akretion,Odoo Community Association (OCA)
Author-email: support@odoo-community.org
Classifier: Programming Language :: Python
Classifier: Framework :: Odoo
Classifier: Framework :: Odoo :: 18.0
Classifier: License :: OSI Approved :: GNU Affero General Public License v3
